all_package_resolver/__init__.py
all_package_resolver/downloaders/__init__.py
all_package_resolver/downloaders/downloader.py
all_package_resolver/downloaders/lang/__init__.py
all_package_resolver/downloaders/lang/lang_downloader.py
all_package_resolver/downloaders/lang/node_downloader.py
all_package_resolver/downloaders/lang/python_downloader.py
all_package_resolver/downloaders/os/__init__.py
all_package_resolver/downloaders/os/alpine_downloader.py
all_package_resolver/downloaders/os/centos_downloader.py
all_package_resolver/downloaders/os/os_downloader.py
all_package_resolver/downloaders/os/ubuntu_downloader.py
all_package_resolver/logger.py
all_package_resolver/main.py
all_package_resolver/parameters.py
all_package_resolver/state.py
all_package_resolver/utils.py
all_package_resolver-0.0.8.dist-info/METADATA
all_package_resolver-0.0.8.dist-info/WHEEL
all_package_resolver-0.0.8.dist-info/entry_points.txt
all_package_resolver-0.0.8.dist-info/RECORD
