Metadata-Version: 2.1
Name: all-package-resolver
Version: 0.0.8
Summary: This package is for those who need to download a package, with ALL of its dependencies. Not install, download only.
License: MIT
Author: benjkr
Author-email: 69110197+benjkr@users.noreply.github.com
Requires-Python: >=3.10,<4.0
Classifier: License :: OSI Approved :: MIT License
Classifier: Programming Language :: Python :: 3
Classifier: Programming Language :: Python :: 3.10
Classifier: Programming Language :: Python :: 3.11
Requires-Dist: colorlog (>=6.7.0,<7.0.0)
Requires-Dist: docker (>=6.1.3,<7.0.0)
Requires-Dist: human-readable (>=1.3.4,<2.0.0)
Requires-Dist: pathlib2 (>=2.3.7.post1,<3.0.0)
Requires-Dist: rich (>=13.5.2,<14.0.0)
Requires-Dist: typer (>=0.9.0,<0.10.0)
Project-URL: homepage, https://pypi.org/project/all-package-resolver/
Project-URL: repository, https://github.com/benjkr/package-resolver
